TopoPyScale/__init__.py
TopoPyScale/fetch_dem.py
TopoPyScale/fetch_era5.py
TopoPyScale/fetch_era5_zarr.py
TopoPyScale/fetch_ifs_forecast.py
TopoPyScale/meteo_util.py
TopoPyScale/sim_fsm.py
TopoPyScale/sim_fsm2oshd.py
TopoPyScale/solar_geom.py
TopoPyScale/topo_compare.py
TopoPyScale/topo_export.py
TopoPyScale/topo_obs.py
TopoPyScale/topo_param.py
TopoPyScale/topo_plot.py
TopoPyScale/topo_scale.py
TopoPyScale/topo_scale_zarr.py
TopoPyScale/topo_sub.py
TopoPyScale/topo_utils.py
TopoPyScale/topoclass.py
topopyscale-0.3.3.dist-info/licenses/LICENSE
topopyscale-0.3.3.dist-info/WHEEL
topopyscale-0.3.3.dist-info/METADATA
topopyscale-0.3.3.dist-info/RECORD
