Metadata-Version: 2.4
Name: TopoPyScale
Version: 0.3.3
Summary: TopoPyScale, a Python package to perform simplistic climate downscaling at the hillslope scale.
Keywords: climate,downscaling,meteorology,xarray
Author: Joel Fiddes, Kristoffer Aalstad
Author-email: Simon Filhol <simon.filhol@meteo.fr>
Requires-Python: >=3.13
License-Expression: MIT
Classifier: Development Status :: 4 - Beta
Classifier: Intended Audience :: Science/Research
Classifier: Topic :: Scientific/Engineering :: Visualization
Classifier: Topic :: Scientific/Engineering :: Hydrology
Classifier: Topic :: Scientific/Engineering :: Atmospheric Science
Classifier: Programming Language :: Python :: 3.13
License-File: LICENSE
Requires-Dist: xarray[complete]>=2025.07.1
Requires-Dist: rioxarray
Requires-Dist: matplotlib
Requires-Dist: scikit-learn
Requires-Dist: pandas
Requires-Dist: geopandas
Requires-Dist: numpy
Requires-Dist: netcdf4
Requires-Dist: h5netcdf
Requires-Dist: pvlib
Requires-Dist: topocalc
Requires-Dist: cdsapi
Requires-Dist: rasterio
Requires-Dist: pyproj
Requires-Dist: dask
Requires-Dist: configobj
Requires-Dist: munch
Requires-Dist: cdo
Requires-Dist: gitpython
Requires-Dist: era5_downloader
Requires-Dist: bs4
Requires-Dist: cfgrib
Project-URL: Documentation, https://topopyscale.readthedocs.io/en/latest/
Project-URL: Download, https://github.com/ArcticSnow/TopoPyScale/releases/latest
Project-URL: Examples, https://github.com/ArcticSnow/TopoPyScale_examples
Project-URL: Home, https://topopyscale.readthedocs.io
Project-URL: Source, https://github.com/ArcticSnow/TopoPyScale
